{
  "pods": [
    {
      "id": 1,
      "podName": "The Bite on Belmont",
      "tables": {
        "uncovered": "3",
        "covered": "7"
      },
      "restrooms": "Portable",
      "beverages": "Beer cart",
      "parking": "Street",
      "bikeParking": "None",
      "location": "4255 SE Belmont St Portland, OR 97215",
      "image": "./images/pod-biteOnBelmont.jpg",
      "count": 9,
      "carts": [
        {
          "cartName": "Kind Coffee",
          "type": "Coffee and bagels",
          "vegOptions": true,
          "hours": {
            "sunday": "8am - 2pm",
            "monday": "Closed",
            "tuesday": "8am - 2pm",
            "wednesday": "8am - 2pm",
            "thursday": "8am - 2pm",
            "friday": "8am - 2pm",
            "saturday": "8am - 2pm"
          },
          "image": "images/cart-kindCoffee.jpg",
          "menu": "images/cart-kindCoffee-menu.jpg",
          "topFive": {
            "1": "Drip Coffee",
            "2": "Latte",
            "3": "Bagel with cream cheese",
            "4": "Bagel with lox",
            "5": "Dirty Chai"
          }
        },
        {
          "cartName": "Brazilian House",
          "type": "Brazilian",
          "vegOptions": true,
          "hours": {
            "sunday": "11am - 9pm",
            "monday": "11am - 9pm",
            "tuesday": "11am - 9pm",
            "wednesday": "11am - 9pm",
            "thursday": "11am - 9pm",
            "friday": "11am - 9pm",
            "saturday": "11am - 9pm"
          },
          "image": "images/cart-brazilianHouse.jpg",
          "menu": "images/cart-brazilianHouse-Menu.jpg",
          "topFive": {
            "1": "Coxinha",
            "2": "Moqueca",
            "3": "Feijoada",
            "4": "Tropeiro",
            "5": "Petisco"
          }
        }
      ]
    },
    {
      "id": 2,
      "podName": "Hinterland",
      "tables": {
        "uncovered": "0",
        "covered": "24"
      },
      "restrooms": "2 indoor restrooms",
      "beverages": "Full indoor bar",
      "parking": "street",
      "bikeParking": "yes",
      "location": "2216 SE 50th Ave, Portland, OR 97215",
      "image": "images/pod-hinterland.jpeg",
      "count": 9,
      "carts": [
        {
          "cartName": "Kind Coffee",
          "type": "Coffee and bagels",
          "vegOptions": true,
          "hours": {
            "sunday": "8am - 2pm",
            "monday": "Closed",
            "tuesday": "8am - 2pm",
            "wednesday": "8am - 2pm",
            "thursday": "8am - 2pm",
            "friday": "8am - 2pm",
            "saturday": "8am - 2pm"
          },
          "image": "images/cart-kindCoffee.jpg",
          "menu": "images/cart-kindCoffee-menu.jpg",
          "topFive": {
            "1": "Drip Coffee",
            "2": "Latte",
            "3": "Bagel with cream cheese",
            "4": "Bagel with lox",
            "5": "Dirty Chai"
          }
        },
        {
          "cartName": "Brazilian House",
          "type": "Brazilian",
          "vegOptions": true,
          "hours": {
            "sunday": "11am - 9pm",
            "monday": "11am - 9pm",
            "tuesday": "11am - 9pm",
            "wednesday": "11am - 9pm",
            "thursday": "11am - 9pm",
            "friday": "11am - 9pm",
            "saturday": "11am - 9pm"
          },
          "image": "images/cart-brazilianHouse.jpg",
          "menu": "images/cart-brazilianHouse-Menu.jpg",
          "topFive": {
            "1": "Coxinha",
            "2": "Moqueca",
            "3": "Feijoada",
            "4": "Tropeiro",
            "5": "Petisco"
          }
        }
      ]
    },
    {
      "id": 3,
      "podName": "Hawthorne Asylum",
      "tables": {
        "uncovered": "3",
        "covered": "7"
      },
      "restrooms": "Portable",
      "beverages": "Beer cart",
      "parking": "Street",
      "bikeParking": "None",
      "location": "1080 SE Madison St, Portland, OR 97214",
      "image": "images/pod-asylum.jpg",
      "count": 9,
      "carts": [
        {
          "cartName": "Kind Coffee",
          "type": "Coffee and bagels",
          "vegOptions": true,
          "hours": {
            "sunday": "8am - 2pm",
            "monday": "Closed",
            "tuesday": "8am - 2pm",
            "wednesday": "8am - 2pm",
            "thursday": "8am - 2pm",
            "friday": "8am - 2pm",
            "saturday": "8am - 2pm"
          },
          "image": "URL",
          "menu": "URL",
          "topFive": {
            "1": "Item",
            "2": "Item",
            "3": "Item",
            "4": "Item",
            "5": "Item"
          }
        }
      ]
    },
    {
      "id": 4,
      "podName": "Portland Mercado",
      "tables": {
        "uncovered": "0",
        "covered": "22"
      },
      "restrooms": "Portable",
      "beverages": "Beer cart",
      "parking": "Medium Sized Lot",
      "bikeParking": "Yes",
      "location": "7238 SE Foster Rd, Portland, OR 97206",
      "image": "images/pod-Mercado.jpg",
      "count": 9,
      "carts": [
        {
          "cartName": "Kind Coffee",
          "type": "Coffee and bagels",
          "vegOptions": true,
          "hours": {
            "sunday": "8am - 2pm",
            "monday": "Closed",
            "tuesday": "8am - 2pm",
            "wednesday": "8am - 2pm",
            "thursday": "8am - 2pm",
            "friday": "8am - 2pm",
            "saturday": "8am - 2pm"
          },
          "image": "URL",
          "menu": "URL",
          "topFive": {
            "1": "Item",
            "2": "Item",
            "3": "Item",
            "4": "Item",
            "5": "Item"
          }
        }
      ]
    },
    {
      "id": 5,
      "podName": "Lil America",
      "tables": {
        "uncovered": "0",
        "covered": "7"
      },
      "restrooms": "Portable",
      "beverages": "Beer cart",
      "parking": "Street",
      "bikeParking": "None",
      "location": "1015 SE Stark St, Portland, OR 97214",
      "image": "images/pod-lilAmerica.jpg",
      "count": 9,
      "carts": [
        {
          "cartName": "Kind Coffee",
          "type": "Coffee and bagels",
          "vegOptions": true,
          "hours": {
            "sunday": "8am - 2pm",
            "monday": "Closed",
            "tuesday": "8am - 2pm",
            "wednesday": "8am - 2pm",
            "thursday": "8am - 2pm",
            "friday": "8am - 2pm",
            "saturday": "8am - 2pm"
          },
          "image": "URL",
          "menu": "URL",
          "topFive": {
            "1": "Item",
            "2": "Item",
            "3": "Item",
            "4": "Item",
            "5": "Item"
          }
        }
      ]
    },
    {
      "podName": "The Yard at Montavilla",
      "tables": {
        "uncovered": "6",
        "covered": "0"
      },
      "restrooms": "Portable",
      "beverages": "Beer cart",
      "parking": "Street",
      "bikeParking": "None",
      "location": "8220 NE Davis St, Portland, OR 97220",
      "image": "images/pod-yard-montavilla.jpg",
      "count": 9,
      "carts": [
        {
          "cartName": "Kind Coffee",
          "type": "Coffee and bagels",
          "vegOptions": true,
          "hours": {
            "sunday": "8am - 2pm",
            "monday": "Closed",
            "tuesday": "8am - 2pm",
            "wednesday": "8am - 2pm",
            "thursday": "8am - 2pm",
            "friday": "8am - 2pm",
            "saturday": "8am - 2pm"
          },
          "image": "URL",
          "menu": "URL",
          "topFive": {
            "1": "Item",
            "2": "Item",
            "3": "Item",
            "4": "Item",
            "5": "Item"
          }
        }
      ]
    },
    {
      "podName": "Ben Bears Beer Bar",
      "tables": {
        "uncovered": "3",
        "covered": "7"
      },
      "restrooms": "Portable",
      "beverages": "Beer cart",
      "parking": "Street",
      "bikeParking": "None",
      "location": "5029 SE Division St, Portland, OR 97206",
      "image": "images/pod-benbears.jpg",
      "count": 9,
      "carts": [
        {
          "cartName": "Kind Coffee",
          "type": "Coffee and bagels",
          "vegOptions": true,
          "hours": {
            "sunday": "8am - 2pm",
            "monday": "Closed",
            "tuesday": "8am - 2pm",
            "wednesday": "8am - 2pm",
            "thursday": "8am - 2pm",
            "friday": "8am - 2pm",
            "saturday": "8am - 2pm"
          },
          "image": "URL",
          "menu": "URL",
          "topFive": {
            "1": "Item",
            "2": "Item",
            "3": "Item",
            "4": "Item",
            "5": "Item"
          }
        }
      ]
    },
    {
      "podName": "The Lot at St. John's Marketplace",
      "tables": {
        "uncovered": "3",
        "covered": "7"
      },
      "restrooms": "Portable",
      "beverages": "Beer cart",
      "parking": "Street",
      "bikeParking": "None",
      "location": "3560 SE Powell Blvd Portland, OR 97202",
      "image": "images/pod-stJohns.jpg",
      "count": 9,
      "carts": [
        {
          "cartName": "Kind Coffee",
          "type": "Coffee and bagels",
          "vegOptions": true,
          "hours": {
            "sunday": "8am - 2pm",
            "monday": "Closed",
            "tuesday": "8am - 2pm",
            "wednesday": "8am - 2pm",
            "thursday": "8am - 2pm",
            "friday": "8am - 2pm",
            "saturday": "8am - 2pm"
          },
          "image": "URL",
          "menu": "URL",
          "topFive": {
            "1": "Item",
            "2": "Item",
            "3": "Item",
            "4": "Item",
            "5": "Item"
          }
        }
      ]
    },
    {
      "podName": "Midtown Beer Garden",
      "tables": {
        "uncovered": "3",
        "covered": "7"
      },
      "restrooms": "Portable",
      "beverages": "Beer cart",
      "parking": "Street",
      "bikeParking": "None",
      "location": "431 SW Harvey Milk St, Portland, OR 97204",
      "image": "images/pod-midtownBeerGarden.jpg",
      "count": 27,
      "carts": [
        {
          "cartName": "Kind Coffee",
          "type": "Coffee and bagels",
          "vegOptions": true,
          "hours": {
            "sunday": "8am - 2pm",
            "monday": "Closed",
            "tuesday": "8am - 2pm",
            "wednesday": "8am - 2pm",
            "thursday": "8am - 2pm",
            "friday": "8am - 2pm",
            "saturday": "8am - 2pm"
          },
          "image": "URL",
          "menu": "URL",
          "topFive": {
            "1": "Item",
            "2": "Item",
            "3": "Item",
            "4": "Item",
            "5": "Item"
          }
        }
      ]
    },
    {
      "podName": "Pioneer Courthouse Square",
      "tables": {
        "uncovered": "3",
        "covered": "7"
      },
      "restrooms": "Portable",
      "beverages": "Beer cart",
      "parking": "Street",
      "bikeParking": "None",
      "location": "701 SW 6th Ave, Portland, OR 97204",
      "image": "images/pod-pioneersquare.jpg",
      "count": 9,
      "carts": [
        {
          "cartName": "Kind Coffee",
          "type": "Coffee and bagels",
          "vegOptions": true,
          "hours": {
            "sunday": "8am - 2pm",
            "monday": "Closed",
            "tuesday": "8am - 2pm",
            "wednesday": "8am - 2pm",
            "thursday": "8am - 2pm",
            "friday": "8am - 2pm",
            "saturday": "8am - 2pm"
          },
          "image": "URL",
          "menu": "URL",
          "topFive": {
            "1": "Item",
            "2": "Item",
            "3": "Item",
            "4": "Item",
            "5": "Item"
          }
        }
      ]
    },
    {
      "podName": "PSU",
      "tables": {
        "uncovered": "3",
        "covered": "7"
      },
      "restrooms": "Portable",
      "beverages": "Beer cart",
      "parking": "Street",
      "bikeParking": "None",
      "location": "4th Ave And Sw College St Portland, OR 97201",
      "image": "images/pod-PSU.webp",
      "count": 9,
      "carts": [
        {
          "cartName": "Kind Coffee",
          "type": "Coffee and bagels",
          "vegOptions": true,
          "hours": {
            "sunday": "8am - 2pm",
            "monday": "Closed",
            "tuesday": "8am - 2pm",
            "wednesday": "8am - 2pm",
            "thursday": "8am - 2pm",
            "friday": "8am - 2pm",
            "saturday": "8am - 2pm"
          },
          "image": "URL",
          "menu": "URL",
          "topFive": {
            "1": "Item",
            "2": "Item",
            "3": "Item",
            "4": "Item",
            "5": "Item"
          }
        }
      ]
    },
    {
      "podName": "3rd Ave Pod",
      "tables": {
        "uncovered": "3",
        "covered": "7"
      },
      "restrooms": "Portable",
      "beverages": "Beer cart",
      "parking": "Street",
      "bikeParking": "None",
      "location": "SW 3rd Ave &, SW Harvey Milk St, Portland, OR 97204",
      "image": "images/pod-3rdAve.jpg",
      "count": 9,
      "carts": [
        {
          "cartName": "Kind Coffee",
          "type": "Coffee and bagels",
          "vegOptions": true,
          "hours": {
            "sunday": "8am - 2pm",
            "monday": "Closed",
            "tuesday": "8am - 2pm",
            "wednesday": "8am - 2pm",
            "thursday": "8am - 2pm",
            "friday": "8am - 2pm",
            "saturday": "8am - 2pm"
          },
          "image": "URL",
          "menu": "URL",
          "topFive": {
            "1": "Item",
            "2": "Item",
            "3": "Item",
            "4": "Item",
            "5": "Item"
          }
        }
      ]
    },
    {
      "podName": "Cart Blocks",
      "tables": {
        "uncovered": "3",
        "covered": "7"
      },
      "restrooms": "Portable",
      "beverages": "Beer cart",
      "parking": "Street",
      "bikeParking": "None",
      "location": "770 W Burnside St, Portland, OR 97209",
      "image": "images/pod-cart-blocks.jpg",
      "count": 9,
      "carts": [
        {
          "cartName": "Kind Coffee",
          "type": "Coffee and bagels",
          "vegOptions": true,
          "hours": {
            "sunday": "8am - 2pm",
            "monday": "Closed",
            "tuesday": "8am - 2pm",
            "wednesday": "8am - 2pm",
            "thursday": "8am - 2pm",
            "friday": "8am - 2pm",
            "saturday": "8am - 2pm"
          },
          "image": "URL",
          "menu": "URL",
          "topFive": {
            "1": "Item",
            "2": "Item",
            "3": "Item",
            "4": "Item",
            "5": "Item"
          }
        }
      ]
    },
    {
      "podName": "2nd Ave Pod",
      "tables": {
        "uncovered": "3",
        "covered": "7"
      },
      "restrooms": "Portable",
      "beverages": "Beer cart",
      "parking": "Street",
      "bikeParking": "None",
      "location": "321 SW 2nd Ave, Portland, OR 97204",
      "image": "images/pod-2nd-Ave.jpg",
      "count": 9,
      "carts": [
        {
          "cartName": "Kind Coffee",
          "type": "Coffee and bagels",
          "vegOptions": true,
          "hours": {
            "sunday": "8am - 2pm",
            "monday": "Closed",
            "tuesday": "8am - 2pm",
            "wednesday": "8am - 2pm",
            "thursday": "8am - 2pm",
            "friday": "8am - 2pm",
            "saturday": "8am - 2pm"
          },
          "image": "URL",
          "menu": "URL",
          "topFive": {
            "1": "Item",
            "2": "Item",
            "3": "Item",
            "4": "Item",
            "5": "Item"
          }
        }
      ]
    },
    {
      "podName": "Cartside Food Cart Pod",
      "tables": {
        "uncovered": "3",
        "covered": "7"
      },
      "restrooms": "Portable",
      "beverages": "Beer cart",
      "parking": "Street",
      "bikeParking": "None",
      "location": "1825 N Williams Ave, Portland, OR 97227",
      "image": "images/pod-CartSide.jpg",
      "count": 9,
      "carts": [
        {
          "cartName": "Kind Coffee",
          "type": "Coffee and bagels",
          "vegOptions": true,
          "hours": {
            "sunday": "8am - 2pm",
            "monday": "Closed",
            "tuesday": "8am - 2pm",
            "wednesday": "8am - 2pm",
            "thursday": "8am - 2pm",
            "friday": "8am - 2pm",
            "saturday": "8am - 2pm"
          },
          "image": "URL",
          "menu": "URL",
          "topFive": {
            "1": "Item",
            "2": "Item",
            "3": "Item",
            "4": "Item",
            "5": "Item"
          }
        }
      ]
    },
    {
      "podName": "Killingsworth Station",
      "tables": {
        "uncovered": "3",
        "covered": "7"
      },
      "restrooms": "Portable",
      "beverages": "Beer cart",
      "parking": "Street",
      "bikeParking": "None",
      "location": "1331 N Killingsworth St. Portland, OR 97217",
      "image": "images/pod-killingsworth.jpg",
      "count": 9,
      "carts": [
        {
          "cartName": "Kind Coffee",
          "type": "Coffee and bagels",
          "vegOptions": true,
          "hours": {
            "sunday": "8am - 2pm",
            "monday": "Closed",
            "tuesday": "8am - 2pm",
            "wednesday": "8am - 2pm",
            "thursday": "8am - 2pm",
            "friday": "8am - 2pm",
            "saturday": "8am - 2pm"
          },
          "image": "URL",
          "menu": "URL",
          "topFive": {
            "1": "Item",
            "2": "Item",
            "3": "Item",
            "4": "Item",
            "5": "Item"
          }
        }
      ]
    },
    {
      "podName": "NEW POD HERE",
      "tables": {
        "uncovered": "3",
        "covered": "7"
      },
      "restrooms": "Portable",
      "beverages": "Beer cart",
      "parking": "Street",
      "bikeParking": "None",
      "location": "4255 SE Belmont St Portland, OR 97215",
      "image": "images/pod-biteOnBelmont.jpg",
      "count": 9,
      "carts": [
        {
          "cartName": "Kind Coffee",
          "type": "Coffee and bagels",
          "vegOptions": true,
          "hours": {
            "sunday": "8am - 2pm",
            "monday": "Closed",
            "tuesday": "8am - 2pm",
            "wednesday": "8am - 2pm",
            "thursday": "8am - 2pm",
            "friday": "8am - 2pm",
            "saturday": "8am - 2pm"
          },
          "image": "URL",
          "menu": "URL",
          "topFive": {
            "1": "Item",
            "2": "Item",
            "3": "Item",
            "4": "Item",
            "5": "Item"
          }
        }
      ]
    },
    {
      "podName": "NEW POD HERE",
      "tables": {
        "uncovered": "3",
        "covered": "7"
      },
      "restrooms": "Portable",
      "beverages": "Beer cart",
      "parking": "Street",
      "bikeParking": "None",
      "location": "4255 SE Belmont St Portland, OR 97215",
      "image": "images/pod-biteOnBelmont.jpg",
      "count": 9,
      "carts": [
        {
          "cartName": "Kind Coffee",
          "type": "Coffee and bagels",
          "vegOptions": true,
          "hours": {
            "sunday": "8am - 2pm",
            "monday": "Closed",
            "tuesday": "8am - 2pm",
            "wednesday": "8am - 2pm",
            "thursday": "8am - 2pm",
            "friday": "8am - 2pm",
            "saturday": "8am - 2pm"
          },
          "image": "URL",
          "menu": "URL",
          "topFive": {
            "1": "Item",
            "2": "Item",
            "3": "Item",
            "4": "Item",
            "5": "Item"
          }
        }
      ]
    },
    {
      "podName": "NEW POD HERE",
      "tables": {
        "uncovered": "3",
        "covered": "7"
      },
      "restrooms": "Portable",
      "beverages": "Beer cart",
      "parking": "Street",
      "bikeParking": "None",
      "location": "4255 SE Belmont St Portland, OR 97215",
      "image": "images/pod-biteOnBelmont.jpg",
      "count": 9,
      "carts": [
        {
          "cartName": "Kind Coffee",
          "type": "Coffee and bagels",
          "vegOptions": true,
          "hours": {
            "sunday": "8am - 2pm",
            "monday": "Closed",
            "tuesday": "8am - 2pm",
            "wednesday": "8am - 2pm",
            "thursday": "8am - 2pm",
            "friday": "8am - 2pm",
            "saturday": "8am - 2pm"
          },
          "image": "URL",
          "menu": "URL",
          "topFive": {
            "1": "Item",
            "2": "Item",
            "3": "Item",
            "4": "Item",
            "5": "Item"
          }
        }
      ]
    },
    {
      "podName": "NEW POD HERE",
      "tables": {
        "uncovered": "3",
        "covered": "7"
      },
      "restrooms": "Portable",
      "beverages": "Beer cart",
      "parking": "Street",
      "bikeParking": "None",
      "location": "4255 SE Belmont St Portland, OR 97215",
      "image": "images/pod-biteOnBelmont.jpg",
      "count": 9,
      "carts": [
        {
          "cartName": "Kind Coffee",
          "type": "Coffee and bagels",
          "vegOptions": true,
          "hours": {
            "sunday": "8am - 2pm",
            "monday": "Closed",
            "tuesday": "8am - 2pm",
            "wednesday": "8am - 2pm",
            "thursday": "8am - 2pm",
            "friday": "8am - 2pm",
            "saturday": "8am - 2pm"
          },
          "image": "URL",
          "menu": "URL",
          "topFive": {
            "1": "Item",
            "2": "Item",
            "3": "Item",
            "4": "Item",
            "5": "Item"
          }
        }
      ]
    },
    {
      "podName": "NEW POD HERE",
      "tables": {
        "uncovered": "3",
        "covered": "7"
      },
      "restrooms": "Portable",
      "beverages": "Beer cart",
      "parking": "Street",
      "bikeParking": "None",
      "location": "4255 SE Belmont St Portland, OR 97215",
      "image": "images/pod-biteOnBelmont.jpg",
      "count": 9,
      "carts": [
        {
          "cartName": "Kind Coffee",
          "type": "Coffee and bagels",
          "vegOptions": true,
          "hours": {
            "sunday": "8am - 2pm",
            "monday": "Closed",
            "tuesday": "8am - 2pm",
            "wednesday": "8am - 2pm",
            "thursday": "8am - 2pm",
            "friday": "8am - 2pm",
            "saturday": "8am - 2pm"
          },
          "image": "URL",
          "menu": "URL",
          "topFive": {
            "1": "Item",
            "2": "Item",
            "3": "Item",
            "4": "Item",
            "5": "Item"
          }
        }
      ]
    },
    {
      "podName": "NEW POD HERE",
      "tables": {
        "uncovered": "3",
        "covered": "7"
      },
      "restrooms": "Portable",
      "beverages": "Beer cart",
      "parking": "Street",
      "bikeParking": "None",
      "location": "4255 SE Belmont St Portland, OR 97215",
      "image": "images/pod-biteOnBelmont.jpg",
      "count": 9,
      "carts": [
        {
          "cartName": "Kind Coffee",
          "type": "Coffee and bagels",
          "vegOptions": true,
          "hours": {
            "sunday": "8am - 2pm",
            "monday": "Closed",
            "tuesday": "8am - 2pm",
            "wednesday": "8am - 2pm",
            "thursday": "8am - 2pm",
            "friday": "8am - 2pm",
            "saturday": "8am - 2pm"
          },
          "image": "URL",
          "menu": "URL",
          "topFive": {
            "1": "Item",
            "2": "Item",
            "3": "Item",
            "4": "Item",
            "5": "Item"
          }
        }
      ]
    },
    {
      "podName": "NEW POD HERE",
      "tables": {
        "uncovered": "3",
        "covered": "7"
      },
      "restrooms": "Portable",
      "beverages": "Beer cart",
      "parking": "Street",
      "bikeParking": "None",
      "location": "4255 SE Belmont St Portland, OR 97215",
      "image": "images/pod-biteOnBelmont.jpg",
      "count": 9,
      "carts": [
        {
          "cartName": "Kind Coffee",
          "type": "Coffee and bagels",
          "vegOptions": true,
          "hours": {
            "sunday": "8am - 2pm",
            "monday": "Closed",
            "tuesday": "8am - 2pm",
            "wednesday": "8am - 2pm",
            "thursday": "8am - 2pm",
            "friday": "8am - 2pm",
            "saturday": "8am - 2pm"
          },
          "image": "URL",
          "menu": "URL",
          "topFive": {
            "1": "Item",
            "2": "Item",
            "3": "Item",
            "4": "Item",
            "5": "Item"
          }
        }
      ]
    },
    {
      "podName": "NEW POD HERE",
      "tables": {
        "uncovered": "3",
        "covered": "7"
      },
      "restrooms": "Portable",
      "beverages": "Beer cart",
      "parking": "Street",
      "bikeParking": "None",
      "location": "4255 SE Belmont St Portland, OR 97215",
      "image": "images/pod-biteOnBelmont.jpg",
      "count": 9,
      "carts": [
        {
          "cartName": "Kind Coffee",
          "type": "Coffee and bagels",
          "vegOptions": true,
          "hours": {
            "sunday": "8am - 2pm",
            "monday": "Closed",
            "tuesday": "8am - 2pm",
            "wednesday": "8am - 2pm",
            "thursday": "8am - 2pm",
            "friday": "8am - 2pm",
            "saturday": "8am - 2pm"
          },
          "image": "URL",
          "menu": "URL",
          "topFive": {
            "1": "Item",
            "2": "Item",
            "3": "Item",
            "4": "Item",
            "5": "Item"
          }
        }
      ]
    },
    {
      "podName": "NEW POD HERE",
      "tables": {
        "uncovered": "3",
        "covered": "7"
      },
      "restrooms": "Portable",
      "beverages": "Beer cart",
      "parking": "Street",
      "bikeParking": "None",
      "location": "4255 SE Belmont St Portland, OR 97215",
      "image": "images/pod-biteOnBelmont.jpg",
      "count": 9,
      "carts": [
        {
          "cartName": "Kind Coffee",
          "type": "Coffee and bagels",
          "vegOptions": true,
          "hours": {
            "sunday": "8am - 2pm",
            "monday": "Closed",
            "tuesday": "8am - 2pm",
            "wednesday": "8am - 2pm",
            "thursday": "8am - 2pm",
            "friday": "8am - 2pm",
            "saturday": "8am - 2pm"
          },
          "image": "URL",
          "menu": "URL",
          "topFive": {
            "1": "Item",
            "2": "Item",
            "3": "Item",
            "4": "Item",
            "5": "Item"
          }
        }
      ]
    },
    {
      "podName": "NEW POD HERE",
      "tables": {
        "uncovered": "3",
        "covered": "7"
      },
      "restrooms": "Portable",
      "beverages": "Beer cart",
      "parking": "Street",
      "bikeParking": "None",
      "location": "4255 SE Belmont St Portland, OR 97215",
      "image": "images/pod-biteOnBelmont.jpg",
      "count": 9,
      "carts": [
        {
          "cartName": "Kind Coffee",
          "type": "Coffee and bagels",
          "vegOptions": true,
          "hours": {
            "sunday": "8am - 2pm",
            "monday": "Closed",
            "tuesday": "8am - 2pm",
            "wednesday": "8am - 2pm",
            "thursday": "8am - 2pm",
            "friday": "8am - 2pm",
            "saturday": "8am - 2pm"
          },
          "image": "URL",
          "menu": "URL",
          "topFive": {
            "1": "Item",
            "2": "Item",
            "3": "Item",
            "4": "Item",
            "5": "Item"
          }
        }
      ]
    },
    {
      "podName": "NEW POD HERE",
      "tables": {
        "uncovered": "3",
        "covered": "7"
      },
      "restrooms": "Portable",
      "beverages": "Beer cart",
      "parking": "Street",
      "bikeParking": "None",
      "location": "4255 SE Belmont St Portland, OR 97215",
      "image": "images/pod-biteOnBelmont.jpg",
      "count": 9,
      "carts": [
        {
          "cartName": "Kind Coffee",
          "type": "Coffee and bagels",
          "vegOptions": true,
          "hours": {
            "sunday": "8am - 2pm",
            "monday": "Closed",
            "tuesday": "8am - 2pm",
            "wednesday": "8am - 2pm",
            "thursday": "8am - 2pm",
            "friday": "8am - 2pm",
            "saturday": "8am - 2pm"
          },
          "image": "URL",
          "menu": "URL",
          "topFive": {
            "1": "Item",
            "2": "Item",
            "3": "Item",
            "4": "Item",
            "5": "Item"
          }
        }
      ]
    },
    {
      "podName": "NEW POD HERE",
      "tables": {
        "uncovered": "3",
        "covered": "7"
      },
      "restrooms": "Portable",
      "beverages": "Beer cart",
      "parking": "Street",
      "bikeParking": "None",
      "location": "4255 SE Belmont St Portland, OR 97215",
      "image": "images/pod-biteOnBelmont.jpg",
      "count": 9,
      "carts": [
        {
          "cartName": "Kind Coffee",
          "type": "Coffee and bagels",
          "vegOptions": true,
          "hours": {
            "sunday": "8am - 2pm",
            "monday": "Closed",
            "tuesday": "8am - 2pm",
            "wednesday": "8am - 2pm",
            "thursday": "8am - 2pm",
            "friday": "8am - 2pm",
            "saturday": "8am - 2pm"
          },
          "image": "URL",
          "menu": "URL",
          "topFive": {
            "1": "Item",
            "2": "Item",
            "3": "Item",
            "4": "Item",
            "5": "Item"
          }
        }
      ]
    }
  ]
}
